beekeeper/readers/docling/__init__.py
beekeeper/readers/docling/base.py
beekeeper_readers_docling-1.0.1.dist-info/METADATA
beekeeper_readers_docling-1.0.1.dist-info/WHEEL
beekeeper_readers_docling-1.0.1.dist-info/RECORD
