Metadata-Version: 2.4
Name: beekeeper-readers-docling
Version: 1.0.1
Summary: beekeeper readers docling extension
Author-email: Leonardo Furnielis <leonardofurnielis@outlook.com>
License: Apache-2.0
Requires-Python: <4.0,>=3.10
Requires-Dist: beekeeper-core<2.0.0,>=1.0.0
Requires-Dist: docling<3.0.0,>=2.37.0
Provides-Extra: dev
Requires-Dist: ruff>=0.11.13; extra == 'dev'
